epico/__init__.py
epico/__main__.py
epico/dir.py
epico/file.py
epico/thread.py
epico/version.py
epico-0.1.3.dist-info/LICENSE
epico-0.1.3.dist-info/METADATA
epico-0.1.3.dist-info/WHEEL
epico-0.1.3.dist-info/top_level.txt
epico-0.1.3.dist-info/RECORD
