Metadata-Version: 2.1
Name: epico
Version: 0.1.3
Summary: Some epic utilities
Home-page: https://github.com/wk1093/epico
Author: Wyatt K
Author-email: wyattk1093@gmail.com
License: UNKNOWN
Project-URL: GitHub, https://github.com/wk1093/epico
Platform: UNKNOWN
Classifier: Programming Language :: Python :: 3
Classifier: License :: OSI Approved :: MIT License
Classifier: Operating System :: OS Independent
Requires-Python: >=3.6
